{"child_modules": ["django.views.generic.detail", "django.contrib.contenttypes", "django.db.models.constraints", "django.db.backends.base.validation", "django.core.files.uploadedfile", "django.db.models.lookups", "django.template.library", "django.test.utils", "django.test.runner", "django.utils.version", "django.test.client", "django.db.models.options", "django.db.backends.base.base", "django.db.migrations.migration", "django.core.files.uploadhandler", "django.forms.fields", "django.core.management", "django.db.backends.sqlite3", "django.utils", "django.urls", "django.core.files.utils", "django.db.models", "django.core.serializers", "django.core.validators", "django.dispatch", "django.core.signals", "django.db.models.fields.related", "django.core.checks", "django.contrib.auth.models", "django.contrib.auth.signals", "django.core.servers.basehttp", "django.core.handlers.wsgi", "django.template.context", "django.core.management.color", "django.http.request", "django.forms", "django.conf.global_settings", "django.db.models.sql.subqueries", "django.core.exceptions", "django.core.files", "django.test", "django.utils.datastructures", "django.core.serializers.python", "django.middleware.csrf", "django.middleware", "django.template.loaders.base", "django.contrib.contenttypes.fields", "django.apps", "django.utils.html", "django.contrib.postgres.fields.citext", "django.contrib.postgres.fields.jsonb", "django.db.utils", "django.db.models.query_utils", "django.apps.config", "django.db.migrations.operations", "django.db.backends.base.features", "django.contrib.postgres.fields", "django.db.models.base", "django.core.serializers.base", "django.core.checks.messages", "django.db.models.query", "django.views.generic.base", "django.contrib.auth.backends", "django.http.cookie", "django.core.paginator", "django.db.backends.sqlite3.base", "django.contrib.sessions.backends.base", "django.forms.models", "django.db.backends.utils", "django.forms.widgets", "django.db.models.indexes", "django.db.models.deletion", "django.contrib.postgres.fields.mixins", "django.core.management.base", "django.db.models.fields.mixins", "django.urls.conf", "django.db.backends.base.schema", "django.utils.safestring", "django.forms.boundfield", "django.http.response", "django.template", "django.db.migrations.operations.special", "django.db.models.fields.related_descriptors", "django.db.models.fields.proxy", "django.contrib.sessions", "django.db.migrations", "django.urls.converters", "django.views.decorators.csrf", "django.db.backends", "django.db.models.signals", "django.db", "django.db.backends.base.introspection", "django.urls.exceptions", "django.forms.formsets", "django.dispatch.dispatcher", "django.db.models.manager", "django.views.generic.dates", "django.db.migrations.state", "django.db.backends.base.client", "django.db.backends.base.creation", "django.utils.functional", "django.forms.forms", "django.urls.resolvers", "django.forms.utils", "django.db.models.fields.files", "django.core.files.base", "django.contrib.contenttypes.models", "django.template.backends.base", "django.template.utils", "django.views", "django.contrib.auth.validators", "django.utils.encoding", "django.contrib.postgres.fields.ranges", "django.urls.utils", "django.utils.deprecation", "django.db.models.sql.query", "django.db.backends.base", "django.template.engine", "django.core", "django.views.generic.edit", "django.views.generic", "django.views.generic.list", "django.core.handlers", "django.db.migrations.operations.models", "django.db.models.fields", "django.forms.renderers", "django.test.testcases", "django.core.handlers.base", "django.template.exceptions", "django.contrib.sessions.backends", "django.template.loaders", "django.template.defaultfilters", "django.core.files.storage", "django.core.checks.model_checks", "django.contrib.postgres", "django.core.serializers.json", "django.template.smartif", "django.db.models.aggregates", "django.contrib.auth.base_user", "django.template.loader_tags", "django.db.backends.ddl_references", "django.db.models.fields.related_lookups", "django.contrib.postgres.fields.array", "django.utils.tree", "django.db.models.sql.datastructures", "django.views.decorators", "django.contrib", "django.urls.base", "django.db.models.sql.compiler", "django.http", "django.test.signals", "django.db.models.sql", "django.core.servers", "django.db.models.fields.reverse_related", "django.apps.registry", "django.db.migrations.operations.fields", "django.contrib.auth", "django.db.models.sql.where", "django.db.migrations.operations.base", "django.db.models.expressions", "django.core.checks.registry", "django.contrib.postgres.fields.hstore", "django.core.files.images", "django.template.backends", "django.conf", "django.core.wsgi", "django.template.base", "django.template.defaulttags", "django.utils.timezone"], "data_mtime": 1568505580, "dep_lines": [1, 2, 1, 1], "dep_prios": [5, 5, 5, 30], "dependencies": ["typing", "django.utils.version", "builtins", "abc"], "hash": "b744c66ec089d09a12ebf936f79f6d1e", "id": "django", "ignore_all": true, "interface_hash": "3d7fd087d087bc59ff1a9a29d2b32cf1", "mtime": 1568505511, "options": {"allow_redefinition": false, "allow_untyped_globals": false, "always_false": [], "always_true": [], "bazel": false, "check_untyped_defs": false, "disallow_any_decorated": false, "disallow_any_explicit": false, "disallow_any_expr": false, "disallow_any_generics": false, "disallow_any_unimported": false, "disallow_incomplete_defs": true, "disallow_subclassing_any": false, "disallow_untyped_calls": false, "disallow_untyped_decorators": false, "disallow_untyped_defs": false, "follow_imports": "normal", "follow_imports_for_stubs": false, "ignore_errors": false, "ignore_missing_imports": false, "implicit_reexport": true, "local_partial_types": false, "mypyc": false, "new_semantic_analyzer": true, "no_implicit_optional": false, "platform": "linux", "plugins": [], "show_none_errors": true, "strict_equality": false, "strict_optional": true, "strict_optional_whitelist": null, "warn_no_return": true, "warn_return_any": false, "warn_unreachable": false, "warn_unused_ignores": false}, "path": "/usr/local/lib/python3.7/site-packages/django-stubs/__init__.pyi", "size": 432, "suppressed": [], "version_id": "0.720"}